MANIFEST.in
jinja2_markdown.py
readme.md
setup.py
jinja2_markdown.egg-info/PKG-INFO
jinja2_markdown.egg-info/SOURCES.txt
jinja2_markdown.egg-info/dependency_links.txt
jinja2_markdown.egg-info/requires.txt
jinja2_markdown.egg-info/top_level.txt