Metadata-Version: 1.1
Name: jinja2-markdown
Version: 0.0.3
Summary: A jinja2 extension that adds a {% markdown %} tag to templates.
Home-page: http://github.com/danielchatfield/jinja2_markdown_extension
Author: Daniel Chatfield
Author-email: chatfielddaniel@gmail.com
License: UNKNOWN
Platform: UNKNOWN
Classifier: License :: OSI Approved :: MIT License
Classifier: Programming Language :: Python
Classifier: Programming Language :: Python :: 2
Classifier: Programming Language :: Python :: 3
